WMSB/__init__.py
WMSB-0.0.0.dist-info/LICENSE.txt
WMSB-0.0.0.dist-info/METADATA
WMSB-0.0.0.dist-info/WHEEL
WMSB-0.0.0.dist-info/top_level.txt
WMSB-0.0.0.dist-info/RECORD
