Metadata-Version: 2.1
Name: WMSB
Version: 0.0.0
Summary: A package for interfacing with the West Message Service Bus, a REST API.
Home-page: https://upload.pypi.org/legacy/
Author: Westly Durkee
Author-email: westsnetwork@gmail.com
License: UNKNOWN
Platform: UNKNOWN
Classifier: Programming Language :: Python :: 3
Classifier: License :: OSI Approved :: GNU Library or Lesser General Public License (LGPL)
Classifier: Operating System :: OS Independent
Requires-Python: >=3.7
